unhashlib/__init__.py
unhashlib/unhashlib.py
unhashlib/tests/__init__.py
unhashlib/tests/test_unhashlib.py
unhashlib-0.1.0.dist-info/LICENSE.txt
unhashlib-0.1.0.dist-info/METADATA
unhashlib-0.1.0.dist-info/WHEEL
unhashlib-0.1.0.dist-info/top_level.txt
unhashlib-0.1.0.dist-info/RECORD
