Metadata-Version: 2.1
Name: unhashlib
Version: 0.1.0
Summary: A string class enhancement
Home-page: https://github.com/reale/unhashlib
Author: Roberto Reale
Author-email: roberto@reale.me
License: UNKNOWN
Platform: UNKNOWN
Requires-Dist: hashlib
Requires-Dist: requests
